{
  "version": 1,
  "profile_version": "2026-04-04-v3-new-strategies",
  "updated_utc": "2026-04-04T00:00:00Z",
  "profiles": [
    {
      "profile_id": "breakout_bull_core",
      "env_key": "BREAKOUT_SYMBOL_ALLOWLIST",
      "default": true,
      "active_regimes": ["bull_trend", "bull_chop"],
      "strategy_tags": ["inplay_breakout"],
      "min_turnover": 50000000.0,
      "min_atr_pct": 0.30,
      "max_atr_pct": 2.20,
      "min_listing_days": 90,
      "top_n": 12,
      "bt_min_trades": 5,
      "bt_min_net": 0.0,
      "bt_min_pf": 1.0,
      "anchor_symbols": ["BTCUSDT", "ETHUSDT", "SOLUSDT"]
    },
    {
      "profile_id": "breakout_bear_guarded",
      "env_key": "BREAKOUT_SYMBOL_ALLOWLIST",
      "active_regimes": ["bear_chop", "bear_trend"],
      "strategy_tags": ["inplay_breakout"],
      "min_turnover": 75000000.0,
      "min_atr_pct": 0.35,
      "max_atr_pct": 1.80,
      "min_listing_days": 120,
      "top_n": 6,
      "bt_min_trades": 5,
      "bt_min_net": 0.0,
      "bt_min_pf": 1.05,
      "anchor_symbols": ["BTCUSDT", "ETHUSDT", "SOLUSDT"]
    },

    {
      "profile_id": "breakdown_bear_core",
      "env_key": "BREAKDOWN_SYMBOL_ALLOWLIST",
      "default": true,
      "active_regimes": ["bear_chop", "bear_trend"],
      "strategy_tags": ["alt_inplay_breakdown_v1"],
      "min_turnover": 50000000.0,
      "min_atr_pct": 0.30,
      "max_atr_pct": 3.00,
      "min_listing_days": 90,
      "top_n": 8,
      "bt_min_trades": 5,
      "bt_min_net": 0.0,
      "bt_min_pf": 1.0,
      "anchor_symbols": ["BTCUSDT", "ETHUSDT", "SOLUSDT"]
    },
    {
      "profile_id": "breakdown_bull_guarded",
      "env_key": "BREAKDOWN_SYMBOL_ALLOWLIST",
      "active_regimes": ["bull_trend", "bull_chop"],
      "strategy_tags": ["alt_inplay_breakdown_v1"],
      "min_turnover": 75000000.0,
      "min_atr_pct": 0.30,
      "max_atr_pct": 2.20,
      "min_listing_days": 120,
      "top_n": 4,
      "bt_min_trades": 5,
      "bt_min_net": 0.0,
      "bt_min_pf": 1.05,
      "anchor_symbols": ["BTCUSDT", "ETHUSDT", "SOLUSDT"]
    },

    {
      "profile_id": "breakdown2_bear_core",
      "env_key": "BREAKDOWN2_SYMBOL_ALLOWLIST",
      "default": true,
      "active_regimes": ["bear_chop", "bear_trend"],
      "strategy_tags": ["alt_inplay_breakdown_v2"],
      "min_turnover": 20000000.0,
      "min_atr_pct": 0.28,
      "max_atr_pct": 2.50,
      "min_listing_days": 90,
      "top_n": 8,
      "bt_min_trades": 3,
      "bt_min_net": 0.0,
      "bt_min_pf": 1.0,
      "anchor_symbols": ["ADAUSDT", "LINKUSDT", "DOTUSDT", "LTCUSDT"]
    },
    {
      "profile_id": "breakdown2_bull_off",
      "env_key": "BREAKDOWN2_SYMBOL_ALLOWLIST",
      "active_regimes": ["bull_trend", "bull_chop"],
      "strategy_tags": ["alt_inplay_breakdown_v2"],
      "fixed_symbols": []
    },

    {
      "profile_id": "asc1_trend_reduced",
      "env_key": "ASC1_SYMBOL_ALLOWLIST",
      "active_regimes": ["bull_trend", "bear_trend"],
      "strategy_tags": ["alt_sloped_channel_v1"],
      "exclude_symbols": ["BTCUSDT", "ETHUSDT", "SOLUSDT"],
      "min_turnover": 30000000.0,
      "min_atr_pct": 0.28,
      "max_atr_pct": 0.95,
      "min_listing_days": 120,
      "top_n": 4,
      "bt_min_trades": 5,
      "bt_min_net": 0.0,
      "bt_min_pf": 1.0,
      "anchor_symbols": ["LINKUSDT", "ATOMUSDT", "DOTUSDT"]
    },
    {
      "profile_id": "asc1_chop_core",
      "env_key": "ASC1_SYMBOL_ALLOWLIST",
      "default": true,
      "active_regimes": ["bull_chop", "bear_chop"],
      "strategy_tags": ["alt_sloped_channel_v1"],
      "exclude_symbols": ["BTCUSDT", "ETHUSDT", "SOLUSDT"],
      "min_turnover": 30000000.0,
      "min_atr_pct": 0.28,
      "max_atr_pct": 0.95,
      "min_listing_days": 120,
      "top_n": 6,
      "bt_min_trades": 5,
      "bt_min_net": 0.0,
      "bt_min_pf": 1.0,
      "anchor_symbols": ["LINKUSDT", "ATOMUSDT", "DOTUSDT"]
    },

    {
      "profile_id": "arf1_bull_reduced",
      "env_key": "ARF1_SYMBOL_ALLOWLIST",
      "active_regimes": ["bull_trend"],
      "strategy_tags": ["alt_resistance_fade_v1"],
      "exclude_symbols": ["BTCUSDT", "ETHUSDT", "SOLUSDT"],
      "min_turnover": 25000000.0,
      "min_atr_pct": 0.28,
      "max_atr_pct": 1.00,
      "min_listing_days": 120,
      "top_n": 6,
      "bt_min_trades": 5,
      "bt_min_net": 0.0,
      "bt_min_pf": 1.0,
      "anchor_symbols": ["LINKUSDT", "LTCUSDT", "SUIUSDT"]
    },
    {
      "profile_id": "arf1_bear_reduced",
      "env_key": "ARF1_SYMBOL_ALLOWLIST",
      "active_regimes": ["bear_trend"],
      "strategy_tags": ["alt_resistance_fade_v1"],
      "exclude_symbols": ["BTCUSDT", "ETHUSDT", "SOLUSDT"],
      "min_turnover": 25000000.0,
      "min_atr_pct": 0.28,
      "max_atr_pct": 1.00,
      "min_listing_days": 120,
      "top_n": 6,
      "bt_min_trades": 5,
      "bt_min_net": 0.0,
      "bt_min_pf": 1.0,
      "anchor_symbols": ["LINKUSDT", "LTCUSDT", "SUIUSDT"]
    },
    {
      "profile_id": "arf1_chop_core",
      "env_key": "ARF1_SYMBOL_ALLOWLIST",
      "default": true,
      "active_regimes": ["bull_chop", "bear_chop"],
      "strategy_tags": ["alt_resistance_fade_v1"],
      "exclude_symbols": ["BTCUSDT", "ETHUSDT", "SOLUSDT"],
      "min_turnover": 20000000.0,
      "min_atr_pct": 0.28,
      "max_atr_pct": 1.10,
      "min_listing_days": 90,
      "top_n": 8,
      "bt_min_trades": 5,
      "bt_min_net": 0.0,
      "bt_min_pf": 1.0,
      "anchor_symbols": ["LINKUSDT", "LTCUSDT", "SUIUSDT"]
    },

    {
      "profile_id": "asb1_bull_core",
      "env_key": "ASB1_SYMBOL_ALLOWLIST",
      "default": true,
      "active_regimes": ["bull_trend", "bull_chop"],
      "strategy_tags": ["alt_support_bounce_v1"],
      "exclude_symbols": ["BTCUSDT", "ETHUSDT", "SOLUSDT"],
      "min_turnover": 20000000.0,
      "min_atr_pct": 0.28,
      "max_atr_pct": 1.20,
      "min_listing_days": 90,
      "top_n": 8,
      "bt_min_trades": 3,
      "bt_min_net": 0.0,
      "bt_min_pf": 1.0,
      "anchor_symbols": ["ADAUSDT", "LINKUSDT", "SUIUSDT", "DOTUSDT"]
    },
    {
      "profile_id": "asb1_bear_off",
      "env_key": "ASB1_SYMBOL_ALLOWLIST",
      "active_regimes": ["bear_chop", "bear_trend"],
      "strategy_tags": ["alt_support_bounce_v1"],
      "fixed_symbols": []
    },

    {
      "profile_id": "ars1_chop_core",
      "env_key": "ARS1_SYMBOL_ALLOWLIST",
      "default": true,
      "active_regimes": ["bull_chop", "bear_chop"],
      "strategy_tags": ["alt_range_scalp_v1"],
      "min_turnover": 50000000.0,
      "min_atr_pct": 0.25,
      "max_atr_pct": 1.50,
      "min_listing_days": 90,
      "top_n": 6,
      "bt_min_trades": 3,
      "bt_min_net": 0.0,
      "bt_min_pf": 1.0,
      "anchor_symbols": ["BTCUSDT", "ETHUSDT", "SOLUSDT"]
    },
    {
      "profile_id": "ars1_trend_reduced",
      "env_key": "ARS1_SYMBOL_ALLOWLIST",
      "active_regimes": ["bull_trend", "bear_trend"],
      "strategy_tags": ["alt_range_scalp_v1"],
      "min_turnover": 50000000.0,
      "min_atr_pct": 0.25,
      "max_atr_pct": 1.20,
      "min_listing_days": 90,
      "top_n": 3,
      "bt_min_trades": 3,
      "bt_min_net": 0.0,
      "bt_min_pf": 1.0,
      "anchor_symbols": ["BTCUSDT", "ETHUSDT"]
    },

    {
      "profile_id": "avw1_chop_core",
      "env_key": "AVW1_SYMBOL_ALLOWLIST",
      "default": true,
      "active_regimes": ["bull_chop", "bear_chop"],
      "strategy_tags": ["alt_vwap_mean_reversion_v1"],
      "min_turnover": 50000000.0,
      "min_atr_pct": 0.20,
      "max_atr_pct": 1.40,
      "min_listing_days": 90,
      "top_n": 6,
      "bt_min_trades": 3,
      "bt_min_net": 0.0,
      "bt_min_pf": 1.0,
      "anchor_symbols": ["BTCUSDT", "ETHUSDT", "SOLUSDT", "LINKUSDT"]
    },
    {
      "profile_id": "avw1_trend_reduced",
      "env_key": "AVW1_SYMBOL_ALLOWLIST",
      "active_regimes": ["bull_trend", "bear_trend"],
      "strategy_tags": ["alt_vwap_mean_reversion_v1"],
      "min_turnover": 50000000.0,
      "min_atr_pct": 0.20,
      "max_atr_pct": 1.10,
      "min_listing_days": 90,
      "top_n": 3,
      "bt_min_trades": 3,
      "bt_min_net": 0.0,
      "bt_min_pf": 1.0,
      "anchor_symbols": ["BTCUSDT", "ETHUSDT"]
    },

    {
      "profile_id": "ivb1_bull_core",
      "env_key": "IVB1_SYMBOL_ALLOWLIST",
      "default": true,
      "active_regimes": ["bull_trend"],
      "strategy_tags": ["impulse_volume_breakout_v1"],
      "exclude_symbols": ["BTCUSDT", "ETHUSDT"],
      "min_turnover": 40000000.0,
      "min_atr_pct": 0.35,
      "max_atr_pct": 4.5,
      "min_listing_days": 90,
      "top_n": 8,
      "bt_min_trades": 5,
      "bt_min_net": 0.0,
      "bt_min_pf": 1.0,
      "anchor_symbols": ["SOLUSDT", "LINKUSDT", "DOGEUSDT", "TAOUSDT"]
    },
    {
      "profile_id": "ivb1_chop_reduced",
      "env_key": "IVB1_SYMBOL_ALLOWLIST",
      "active_regimes": ["bull_chop"],
      "strategy_tags": ["impulse_volume_breakout_v1"],
      "exclude_symbols": ["BTCUSDT", "ETHUSDT"],
      "min_turnover": 50000000.0,
      "min_atr_pct": 0.40,
      "max_atr_pct": 3.2,
      "min_listing_days": 120,
      "top_n": 5,
      "bt_min_trades": 5,
      "bt_min_net": 0.0,
      "bt_min_pf": 1.0,
      "anchor_symbols": ["SOLUSDT", "LINKUSDT", "DOGEUSDT"]
    },
    {
      "profile_id": "ivb1_bear_off",
      "env_key": "IVB1_SYMBOL_ALLOWLIST",
      "active_regimes": ["bear_chop", "bear_trend"],
      "strategy_tags": ["impulse_volume_breakout_v1"],
      "fixed_symbols": []
    },

    {
      "profile_id": "pf2_all_regimes",
      "env_key": "PF2_SYMBOL_ALLOWLIST",
      "default": true,
      "active_regimes": ["*"],
      "strategy_tags": ["pump_fade_v2"],
      "min_turnover": 50000000.0,
      "min_atr_pct": 0.30,
      "max_atr_pct": 5.00,
      "min_listing_days": 60,
      "top_n": 8,
      "bt_min_trades": 3,
      "bt_min_net": 0.0,
      "bt_min_pf": 1.0,
      "anchor_symbols": ["BTCUSDT", "ETHUSDT", "SOLUSDT", "XRPUSDT"]
    },

    {
      "profile_id": "ets2_all_regimes",
      "env_key": "ETS2_SYMBOL_ALLOWLIST",
      "default": true,
      "active_regimes": ["*"],
      "strategy_tags": ["elder_triple_screen_v2"],
      "min_turnover": 30000000.0,
      "min_atr_pct": 0.28,
      "max_atr_pct": 2.00,
      "min_listing_days": 90,
      "top_n": 6,
      "bt_min_trades": 3,
      "bt_min_net": 0.0,
      "bt_min_pf": 1.0,
      "anchor_symbols": ["BTCUSDT", "ETHUSDT", "SOLUSDT"]
    },

    {
      "profile_id": "midterm_btceth_core",
      "env_key": "MIDTERM_SYMBOLS",
      "default": true,
      "active_regimes": ["*"],
      "fixed_symbols": ["BTCUSDT", "ETHUSDT"]
    }
  ]
}
